tdjson/__init__.py
tdjson/_version.py
tdjson/py.typed
tdjson/tdjson.cpp
tdjson/tdjson_ext.cpython-311-x86_64-linux-gnu.so
tdjson/tdjson_ext.pyi
tdjson.libs/libtdjson-79ebd5c1.so.1.8.60
tdjson-1.8.60.dist-info/METADATA
tdjson-1.8.60.dist-info/WHEEL
tdjson-1.8.60.dist-info/RECORD
tdjson-1.8.60.dist-info/licenses/LICENSE
