Metadata-Version: 2.2
Name: tdjson
Version: 1.8.60
Summary: A high-performance Python binding for TDLib, outperforming ctypes and bundling pre-built binaries for effortless setup on Linux and Windows
Keywords: tdlib,telegram,python-binding,high-performance,linux,windows
Author-Email: AYMEN <let.me.code.safe@gmail.com>
License: MIT
Project-URL: Source, https://github.com/AYMENJD/tdjson
Project-URL: Tracker, https://github.com/AYMENJD/tdjson/issues
Requires-Python: >=3.9
